cmdbase_datacore/__init__.py
cmdbase_datacore/__main__.py
cmdbase_datacore/_version.py
cmdbase_datacore/commands.py
cmdbase_datacore/commons.py
cmdbase_datacore/get.py
cmdbase_datacore/host.py
cmdbase_datacore/port.py
cmdbase_datacore/portconnection.py
cmdbase_datacore/server.py
cmdbase_datacore/virtualdisk.py
cmdbase_datacore-0.0.1a2.dist-info/METADATA
cmdbase_datacore-0.0.1a2.dist-info/WHEEL
cmdbase_datacore-0.0.1a2.dist-info/entry_points.txt
cmdbase_datacore-0.0.1a2.dist-info/top_level.txt
cmdbase_datacore-0.0.1a2.dist-info/RECORD
